csvs_to_sqlite/__init__.py
csvs_to_sqlite/cli.py
csvs_to_sqlite/utils.py
csvs_to_sqlite-1.3.1.dist-info/licenses/LICENSE
csvs_to_sqlite-1.3.1.dist-info/METADATA
csvs_to_sqlite-1.3.1.dist-info/WHEEL
csvs_to_sqlite-1.3.1.dist-info/entry_points.txt
csvs_to_sqlite-1.3.1.dist-info/top_level.txt
csvs_to_sqlite-1.3.1.dist-info/RECORD
