Metadata-Version: 2.4
Name: csvs_to_sqlite
Version: 1.3.1
Summary: Convert CSV files into a SQLite database
Home-page: https://github.com/simonw/csvs-to-sqlite
Author: Simon Willison
License: Apache License, Version 2.0
Classifier: Intended Audience :: Developers
Classifier: Intended Audience :: Science/Research
Classifier: Intended Audience :: End Users/Desktop
Classifier: Topic :: Database
Classifier: License :: OSI Approved :: Apache Software License
Classifier: Programming Language :: Python :: 3.6
Classifier: Programming Language :: Python :: 3.7
Classifier: Programming Language :: Python :: 3.8
Classifier: Programming Language :: Python :: 3.9
License-File: LICENSE
Requires-Dist: click>=7.0
Requires-Dist: dateparser>=1.0
Requires-Dist: pandas>=1.0
Requires-Dist: py-lru-cache~=0.1.4
Requires-Dist: six
Provides-Extra: test
Requires-Dist: pytest; extra == "test"
Requires-Dist: cogapp; extra == "test"
Dynamic: author
Dynamic: classifier
Dynamic: description
Dynamic: description-content-type
Dynamic: home-page
Dynamic: license
Dynamic: license-file
Dynamic: provides-extra
Dynamic: requires-dist
Dynamic: summary
